README.rst
setup.py
ducky/__init__.py
ducky/boot.py
ducky/config.py
ducky/console.py
ducky/debugging.py
ducky/errors.py
ducky/hdt.py
ducky/interfaces.py
ducky/log.py
ducky/machine.py
ducky/patch.py
ducky/profiler.py
ducky/reactor.py
ducky/snapshot.py
ducky/streams.py
ducky/util.py
ducky.egg-info/PKG-INFO
ducky.egg-info/SOURCES.txt
ducky.egg-info/dependency_links.txt
ducky.egg-info/entry_points.txt
ducky.egg-info/not-zip-safe
ducky.egg-info/requires.txt
ducky.egg-info/top_level.txt
ducky/cc/__init__.py
ducky/cc/types.py
ducky/cc/passes/__init__.py
ducky/cc/passes/ast_codegen.py
ducky/cc/passes/ast_constprop.py
ducky/cc/passes/ast_dce.py
ducky/cc/passes/ast_visualise.py
ducky/cc/passes/bt_peephole.py
ducky/cc/passes/bt_simplify.py
ducky/cc/passes/bt_visualise.py
ducky/cpu/__init__.py
ducky/cpu/assemble.py
ducky/cpu/instructions.py
ducky/cpu/registers.py
ducky/cpu/coprocessor/__init__.py
ducky/cpu/coprocessor/control.py
ducky/cpu/coprocessor/math_copro.py
ducky/devices/__init__.py
ducky/devices/keyboard.py
ducky/devices/rtc.py
ducky/devices/snapshot.py
ducky/devices/storage.py
ducky/devices/svga.py
ducky/devices/terminal.py
ducky/devices/tty.py
ducky/mm/__init__.py
ducky/mm/binary.py
ducky/tools/__init__.py
ducky/tools/as.py
ducky/tools/cc.py
ducky/tools/coredump.py
ducky/tools/defs.py
ducky/tools/img.py
ducky/tools/ld.py
ducky/tools/objdump.py
ducky/tools/profile.py
ducky/tools/tui.py
ducky/tools/vm.py