Metadata-Version: 1.1
Name: ducky
Version: 3.0
Summary: Simple virtual CPU/machine simulator
Home-page: https://github.com/happz/ducky
Author: Milos Prchlik
Author-email: happz@happz.cz
License: MIT
Download-URL: https://github.com/happz/ducky/tarball/3.0
Keywords: virtual CPU simulator
Platform: UNKNOWN
Classifier: Development Status :: 4 - Beta
Classifier: Environment :: Console
Classifier: Intended Audience :: Other Audience
Classifier: License :: OSI Approved :: MIT License
Classifier: Operating System :: POSIX :: Linux
Classifier: Programming Language :: Python :: 2.7
Classifier: Programming Language :: Python :: 3.3
Classifier: Programming Language :: Python :: 3.4
Classifier: Programming Language :: Python :: 3.5
Classifier: Programming Language :: Python :: Implementation :: CPython
Classifier: Programming Language :: Python :: Implementation :: PyPy
Classifier: Programming Language :: Forth
Classifier: Programming Language :: Assembly
Classifier: Topic :: Software Development :: Assemblers
Classifier: Topic :: Software Development :: Code Generators
Classifier: Topic :: Software Development :: Compilers
Classifier: Topic :: Software Development :: Interpreters
